{
	"animations": [
		{
			"loop": false,
			"offsets": [
				0,
				0
			],
			"anim": "idle",
			"fps": 24,
			"name": "i",
			"indices": []
		},
		{
			"loop": false,
			"offsets": [
				-6,
				-9
			],
			"anim": "singLEFT",
			"fps": 24,
			"name": "l",
			"indices": []
		},
		{
			"loop": false,
			"offsets": [
				30,
				-15
			],
			"anim": "singDOWN",
			"fps": 24,
			"name": "d",
			"indices": []
		},
		{
			"loop": false,
			"offsets": [
				24,
				38
			],
			"anim": "singUP",
			"fps": 24,
			"name": "u",
			"indices": []
		},
		{
			"loop": false,
			"offsets": [
				13,
				2
			],
			"anim": "singRIGHT",
			"fps": 24,
			"name": "r",
			"indices": []
		}
	],
	"no_antialiasing": false,
	"image": "characters/skiLol",
	"position": [
		-10,
		240
	],
	"healthicon": "sonic",
	"flip_x": false,
	"healthbar_colors": [
		0,
		101,
		204
	],
	"camera_position": [
		-90,
		110
	],
	"sing_duration": 4,
	"scale": 0.7
}